glasz/__init__.py
glasz/_version.py
glasz/_version.pyi
glasz/constants.py
glasz/py.typed
glasz/GGL/__init__.py
glasz/GGL/delta_sigma.py
glasz/kSZ/__init__.py
glasz/kSZ/beam.py
glasz/kSZ/fht.py
glasz/kSZ/pipeline.py
glasz/kSZ/beam_data/act_planck_dr5.01_s08s18_f090_daynight_beam.txt
glasz/kSZ/beam_data/act_planck_dr5.01_s08s18_f150_daynight_beam.txt
glasz/kSZ/beam_data/act_planck_dr5.01_s08s18_f220_daynight_beam.txt
glasz/profiles/__init__.py
glasz/profiles/halo_profiles.py
glasz/profiles/two_halo_term.py
glasz-0.1.3.dist-info/METADATA
glasz-0.1.3.dist-info/WHEEL
glasz-0.1.3.dist-info/licenses/LICENSE
glasz-0.1.3.dist-info/RECORD
